setup.py
bin/goldschmidt
goldschmidt/__init__.py
goldschmidt/goldschmidt.mplstyle
goldschmidt/gui.py
goldschmidt/magnetometer.py
goldschmidt.egg-info/PKG-INFO
goldschmidt.egg-info/SOURCES.txt
goldschmidt.egg-info/dependency_links.txt
goldschmidt.egg-info/requires.txt
goldschmidt.egg-info/top_level.txt