Metadata-Version: 1.1
Name: goldschmidt
Version: 0.0.15
Summary: Readout a GU-3001D Milli-Gauss meter via USB/serial port on a linux system
Home-page: https://github.com/achim1/goldschmidt
Author: Achim Stoessl
Author-email: achim.stoessl@gmail.com
License: GPL
Keywords: magnetometer,gauss,GU-3001D,gaussmeter,Milli-Gauss Meter,readout,physics,engineering,serial,RS-232,USB
Platform: Ubuntu 14.04
Platform: Ubuntu 16.04
Classifier: License :: OSI Approved :: GNU General Public License v3 or later (GPLv3+)
Classifier: Development Status :: 4 - Beta
Classifier: Intended Audience :: Science/Research
Classifier: Intended Audience :: Developers
Classifier: Programming Language :: Python :: 3.5
Classifier: Topic :: Scientific/Engineering :: Physics
